{
	"configurations" : 
	[
		{
			"directories" : 
			[
				{
					"build" : ".",
					"hasInstallRule" : true,
					"minimumCMakeVersion" : 
					{
						"string" : "2.8"
					},
					"projectIndex" : 0,
					"source" : ".",
					"targetIndexes" : 
					[
						0
					]
				}
			],
			"name" : "Debug",
			"projects" : 
			[
				{
					"directoryIndexes" : 
					[
						0
					],
					"name" : "GLEW",
					"targetIndexes" : 
					[
						0
					]
				}
			],
			"targets" : 
			[
				{
					"directoryIndex" : 0,
					"id" : "glew::@6890427a1f51a3e7e1df",
					"jsonFile" : "target-glew-Debug-86380d9438b0a64daec2.json",
					"name" : "glew",
					"projectIndex" : 0
				}
			]
		}
	],
	"kind" : "codemodel",
	"paths" : 
	{
		"build" : "C:/Users/roder/Desktop/Computer graphics/base/ext/glew/out/build/x64-Debug",
		"source" : "C:/Users/roder/Desktop/Computer graphics/base/ext/glew"
	},
	"version" : 
	{
		"major" : 2,
		"minor" : 2
	}
}
